django_rest_paseto_auth-0.1.1.dist-info/METADATA
django_rest_paseto_auth-0.1.1.dist-info/RECORD
django_rest_paseto_auth-0.1.1.dist-info/WHEEL
django_rest_paseto_auth-0.1.1.dist-info/top_level.txt
paseto_auth/__init__.py
paseto_auth/admin.py
paseto_auth/authentication.py
paseto_auth/exceptions.py
paseto_auth/models.py
paseto_auth/serializers.py
paseto_auth/settings.py
paseto_auth/tokens.py
paseto_auth/urls.py
paseto_auth/views.py
paseto_auth/migrations/0001_initial.py
paseto_auth/migrations/__init__.py
