Metadata-Version: 2.1
Name: django-rest-paseto-auth
Version: 0.1.1
Summary: Paseto authentication for Django Rest Framework
Home-page: https://github.com/moiseshiraldo/django-rest-paseto-auth
Author: Moises Hiraldo
Author-email: moiseshiraldo@gmail.com
License: MIT
Platform: UNKNOWN
Classifier: Development Status :: 3 - Alpha
Classifier: Intended Audience :: Developers
Classifier: Environment :: Web Environment
Classifier: Operating System :: OS Independent
Classifier: Programming Language :: Python :: 3.6
Classifier: Framework :: Django :: 2.0
Classifier: License :: OSI Approved :: MIT License
Classifier: Topic :: Internet :: WWW/HTTP
Requires-Python: >=3.6
Requires-Dist: Django (>=2)
Requires-Dist: djangorestframework (>=3.8)
Requires-Dist: paseto (>=0.0.5)
